CMakeLists.txt
LICENSE
MANIFEST.in
README.md
setup.py
cmake/TFLoggerConfig.cmake.in
examples/cpp/CMakeLists.txt
examples/cpp/logger.cc
examples/cpp/reader.cc
examples/python/logger.py
examples/python/reader.py
python/CMakeLists.txt
python/package_init.py
python/pb_init.py
python/tflogger.i
test/CMakeLists.txt
test/event_logger_test.cc
test/record_test.cc
test/tflogger_test.cc
tflogger/event_logger.cc
tflogger/event_logger.h
tflogger/event_reader.cc
tflogger/event_reader.h
tflogger/status.h
tflogger/utils.cc
tflogger/utils.h
tflogger.egg-info/PKG-INFO
tflogger.egg-info/SOURCES.txt
tflogger.egg-info/dependency_links.txt
tflogger.egg-info/not-zip-safe
tflogger.egg-info/requires.txt
tflogger.egg-info/top_level.txt
tflogger/crc32/crc32c.cc
tflogger/crc32/crc32c.h
tflogger/crc32/crc32c_accelerate.cc
tflogger/pb/event.proto
tflogger/pb/summary.proto
tflogger/record/record_reader.cc
tflogger/record/record_reader.h
tflogger/record/record_writer.cc
tflogger/record/record_writer.h