Metadata-Version: 2.1
Name: tflogger
Version: 1.0.1
Summary: TFLogger is a standalone library to read and write events for TensorBoard.
Home-page: https://github.com/shogun-toolbox/tflogger
Author: Viktor Gal
Author-email: viktor.gal@maeth.com
License: Apache 2.0
Platform: UNKNOWN
Classifier: License :: OSI Approved :: Apache Software License
Classifier: Programming Language :: C
Classifier: Programming Language :: C++
Classifier: Programming Language :: Python
Classifier: Development Status :: 5 - Production/Stable
Classifier: Intended Audience :: Developers
